Workbook

Sheet README
A1: AML Quality Assurance Review (Excel)
A3: A no-code AML Quality Assurance (QA) review program — 10 fictional analyst case files, each independently scored against an 8-point QA checklist using a critical-error methodology. Built entirely in Excel formulas.
A5: Why this project: independent testing / quality review of case decisions is one of the pillars of an AML compliance program (the others being policies & procedures, a designated compliance officer, training, and — under the 2021 AML Act — customer due diligence). A QA function doesn't just check whether an analyst closed a case; it checks whether the file, on its own, defensibly supports that closure — the same standard an examiner or auditor would apply. This project applies a QA scoring methodology to AML case review, the same critical-error / zero-tolerance-category approach used in operations and call-center QA programs.
A7: How to use this workbook:
A8: 1. 'QA_Scoring_Rubric' — the 8 criteria, which 3 are critical (zero-tolerance) items, and how the overall outcome is derived.
A9: 2. 'Case_Summaries' — what each analyst actually did: the alert, the investigation, and the disposition reached.
A10: 3. 'QA_Review' — the actual QA assessment. Each case is scored Pass / Partial / Fail against all 8 criteria, with a QA reviewer comment explaining the reasoning. The score, critical-failure flag, and final outcome are all live formulas.
A11: 4. 'QA_Dashboard' — rollup metrics: overall pass rate, pass rate by individual criterion (which QA dimension analysts struggle with most), and a per-analyst breakdown.
A13: The scoring methodology:
A14: - Each of the 8 criteria is scored Pass (1) / Partial (0.5) / Fail (0) for every case.
A15: - THREE criteria are marked CRITICAL: 'Transaction red flags identified?', 'Escalation required?', and 'Final disposition supported by evidence?'. A Fail on any of these overrides the numeric score entirely and produces 'FAIL - Critical Error' — the same design as a zero-tolerance error category in a call-center QA scorecard. A missed red flag or an unsupported disposition isn't a few-points deduction; it's the kind of finding that gets a case reopened.
A16: - Outside of a critical failure, the average score across all 8 criteria determines the outcome: 90%+ is PASS, 75-89% is PASS WITH COACHING, and below 75% is FAIL.
... A25: A note on the sample data: the 10 cases are deliberately weighted toward findings (3 clean passes, 3 pass-with-coaching, 1 fail, 3 critical failures) to showcase the range of things a QA review should catch — a correct escalation with no documented reasoning, a plausible-sounding RFI response nobody cross-checked against KYC, an unnecessary RFI that added friction without changing the outcome, and a clearly missed red flag. This is not meant to represent a real program's typical pass rate.

Sheet QA_Scoring_Rubric
A1: criterion_id | B1: criterion | C1: critical | D1: description
A2: Q1 | B2: KYC information reviewed correctly? | C2: Standard | D2: Did the analyst verify KYC/CDD data on file was current, complete, and consistent with the alert?
A3: Q2 | B3: Customer risk rating appropriate? | C3: Standard | D3: Was the customer's risk rating accurate given current activity, or flagged for re-rating if not?
A4: Q3 | B4: Transaction red flags identified? | C4: CRITICAL | D4: Did the analyst correctly identify all relevant suspicious activity indicators in the alert?
A5: Q4 | B5: Investigation sufficiently documented? | C5: Standard | D5: Is the analytical rationale, evidence reviewed, and conclusion clearly documented in the case file?
A6: Q5 | B6: RFI appropriate? | C6: Standard | D6: Where warranted, did the analyst request additional customer information (RFI) — and was that decision justified either way?
A7: Q6 | B7: Adverse media properly assessed? | C7: Standard | D7: Was negative news screening conducted and any hits properly evaluated and documented?
A8: Q7 | B8: Escalation required? | C8: CRITICAL | D8: Was the decision to escalate (or not escalate) the case correctly made and executed?
A9: Q8 | B9: Final disposition supported by evidence? | C9: CRITICAL | D9: Does the documented evidence actually support the analyst's closure/escalation decision?
A12: OUTCOME LOGIC
A13: Any CRITICAL criterion scored Fail -> FAIL - Critical Error (overrides score)
A14: No critical fail, average score >= 90% -> PASS
A15: No critical fail, average score 75-89% -> PASS WITH COACHING
A16: No critical fail, average score < 75% -> FAIL

Sheet Case_Summaries
A1: case_id | B1: analyst_name | C1: customer_name | D1: account_id | E1: alert_type | F1: alert_date | G1: case_summary | H1: kyc_reviewed_by_analyst | I1: risk_rating_on_file | J1: red_flags_noted_by_analyst | K1: rfi_sent | L1: adverse_media_checked_by_analyst | M1: escalated_by_analyst | N1: sar_filed | O1: final_disposition_by_analyst
A2: QA-001 | B2: Jordan Ellis | C2: Rebecca Lin | D2: AC-10441 | E2: Structuring Alert | F2: 2026-01-14 | G2: Multiple cash deposits flagged near the CTR threshold. Analyst reviewed 6 months of account history, confirmed the pattern matched the customer's documented payroll/freelance income cycle, and compared deposit timing against invoicing records the customer had on file. | H2: Yes | I2: Medium | J2: Yes | K2: No | L2: Yes | M2: No | N2: No | O2: Cleared - No Further Action
A3: QA-002 | B3: Morgan Hale | C3: Nour Haddad | D3: AC-20117 | E3: Large Wire Alert | F3: 2026-01-20 | G3: Outbound wire to a Medium-risk jurisdiction for a stated real estate purchase. Analyst sent an RFI requesting purchase agreement documentation even though the customer's file already contained a notarized sale contract sufficient to support the wire on its own. | H3: Yes | I3: Medium | J3: Yes | K3: Yes | L3: Yes | M3: No | N3: No | O3: Cleared - No Further Action
A4: QA-003 | B4: Taylor Brooks | C4: Carlos Mendez | D4: AC-30288 | E4: Onboarding KYC Review | F4: 2026-02-02 | G4: New PEP customer onboarding. Analyst obtained full source-of-wealth documentation, ran adverse media screening, applied the High risk rating per policy, and routed the file for senior sign-off before account activation. | H4: Yes | I4: High | J4: Yes | K4: Yes | L4: Yes | M4: Yes | N4: No | O4: Approved - Enhanced Due Diligence Applied
A5: QA-004 | B5: Casey Nguyen | C5: Everline Trading DMCC | D5: AC-40556 | E5: Cash-Intensive Business Alert | F5: 2026-02-11 | G5: Cash-intensive business account showing deposit volume above the profile on file. Analyst correctly escalated the case to the senior investigator queue per policy, but the case notes contain only the escalation timestamp with no written rationale for why the deposits exceeded reasonable expectations for the stated business type. | H5: Yes | I5: High | J5: Yes | K5: No | L5: Yes | M5: Yes | N5: No | O5: Escalated - Referred to Senior Investigator
A6: QA-005 | B6: Morgan Hale | C6: Anatoly Sokolov | D6: AC-50902 | E6: Structuring Alert | F6: 2026-02-25 | G6: Repeated cash deposits just under the CTR threshold across three consecutive business days. Analyst documented each deposit, the pattern against the customer's account history, cross-referenced the customer's stated occupation, and filed a SAR with a clear narrative. | H6: Yes | I6: Medium | J6: Yes | K6: No | L6: Yes | M6: Yes | N6: Yes | O6: Escalated - SAR Filed
A7: QA-006 | B7: Riley Chen | C7: Consolidated Metals JSC | D7: AC-61174 | E7: KYC Refresh / RFI Response Review | F7: 2026-03-04 | G7: Customer submitted an RFI response with a business activity description and supporting invoices. Analyst accepted the response and closed the review without comparing the stated business activity against the company registration details already on file in the KYC record, which listed a materially different business purpose. | H7: No | I7: Medium | J7: Yes | K7: Yes | L7: No | M7: No | N7: No | O7: Cleared - No Further Action
A8: QA-007 | B8: Casey Nguyen | C8: Silverline Trading FZE | D8: AC-71330 | E8: Transaction Monitoring Alert | F8: 2026-03-13 | G8: Alert triggered on rapid fund movement. Analyst reviewed the flagged account in isolation and did not review the case tool's link-analysis panel, which showed the same funds moving through two related accounts opened by the same beneficial owner within 48 hours. | H8: Yes | I8: High | J8: No | K8: No | L8: Yes | M8: No | N8: No | O8: Cleared - No Further Action
A9: QA-008 | B9: Riley Chen | C9: Global Freight Solutions Ltd | D9: AC-81502 | E9: Periodic EDD Review | F9: 2026-03-11 | G9: Scheduled periodic review of a high-risk trade finance customer. Government ID for one of two listed beneficial owners on file had expired and was not flagged for refresh. Transaction review and escalation decision were otherwise sound, but the file's documentation of the rationale for continuing the relationship was thinner than the policy standard requires. | H9: Partial | I9: High | J9: Yes | K9: No | L9: Yes | M9: Yes | N9: No | O9: Approved - Continue Relationship with Enhanced Monitoring
A10: QA-009 | B10: Taylor Brooks | C10: Northbridge Capital Partners | D10: AC-91687 | E10: Periodic Review - Adverse Media Hit | F10: 2026-03-19 | G10: Negative news screening returned a hit referencing a regulatory enforcement action tied to an affiliated entity. Case notes state only 'media reviewed, not relevant' with no explanation of what was found, no comparison against the customer's current activity, and no escalation to the MLRO despite policy requiring one for any confirmed regulatory-action hit. | H10: Yes | I10: High | J10: Yes | K10: No | L10: No | M10: No | N10: No | O10: Cleared - No Further Action
A11: QA-010 | B11: Jordan Ellis | C11: Amara Diallo | D11: AC-10229 | E11: Transaction Monitoring Alert | F11: 2026-03-27 | G11: Alert on an unusual international wire pattern. Case was closed with a brief note referencing the wire but with no documented comparison against the customer's account history, only a partial notation of which typology indicators were considered, and no risk-rating cross-check. | H11: No | I11: Medium | J11: Partial | K11: No | L11: No | M11: No | N11: No | O11: Cleared - No Further Action

Sheet QA_Review
A1: case_id | B1: customer_name | C1: analyst_name | D1: Q1_kyc_reviewed | E1: Q2_risk_rating_appropriate | F1: Q3_red_flags_identified (CRITICAL) | G1: Q4_investigation_documented | H1: Q5_rfi_appropriate | I1: Q6_adverse_media_assessed | J1: Q7_escalation_required (CRITICAL) | K1: Q8_disposition_supported (CRITICAL) | L1: qa_reviewer_comments | M1: score_pct | N1: critical_failure | O1: qa_outcome
A2: QA-001 | B2: Rebecca Lin | C2: Jordan Ellis | D2: Pass | E2: Pass | F2: Pass | G2: Pass | H2: Pass | I2: Pass | J2: Pass | K2: Pass | L2: Clean file. KYC current, red flags correctly assessed against documented income pattern, no RFI needed and correctly not sent, clearance fully supported by the account history reviewed. | M2: =(COUNTIF(D2:K2,"Pass")*1+COUNTIF(D2:K2,"Partial")*0.5)/8 -> 1 | N2: =IF(OR(F2="Fail",J2="Fail",K2="Fail"),"YES","NO") -> NO | O2: =IF(N2="YES","FAIL - Critical Error",IF(M2>=0.9,"PASS",IF(M2>=0.75,"PASS WITH COACHING","FAIL"))) -> PASS
A3: QA-002 | B3: Nour Haddad | C3: Morgan Hale | D3: Pass | E3: Pass | F3: Pass | G3: Partial | H3: Partial | I3: Pass | J3: Pass | K3: Pass | L3: Disposition itself is sound, but two things drag this down: the RFI added a week of processing delay and customer friction for information the file already contained, and the case notes don't explain why the RFI was sent given the existing documentation. Coaching point: check the file for existing supporting documentation before sending an RFI, and if one is sent anyway, document why. | M3: =(COUNTIF(D3:K3,"Pass")*1+COUNTIF(D3:K3,"Partial")*0.5)/8 -> 0.875 | N3: =IF(OR(F3="Fail",J3="Fail",K3="Fail"),"YES","NO") -> NO | O3: =IF(N3="YES","FAIL - Critical Error",IF(M3>=0.9,"PASS",IF(M3>=0.75,"PASS WITH COACHING","FAIL"))) -> PASS WITH COACHING
A4: QA-003 | B4: Carlos Mendez | C4: Taylor Brooks | D4: Pass | E4: Pass | F4: Pass | G4: Pass | H4: Pass | I4: Pass | J4: Pass | K4: Pass | L4: Thorough PEP onboarding file. EDD, source-of-wealth documentation, adverse media, and escalation for sign-off are all present and well-documented. | M4: =(COUNTIF(D4:K4,"Pass")*1+COUNTIF(D4:K4,"Partial")*0.5)/8 -> 1 | N4: =IF(OR(F4="Fail",J4="Fail",K4="Fail"),"YES","NO") -> NO | O4: =IF(N4="YES","FAIL - Critical Error",IF(M4>=0.9,"PASS",IF(M4>=0.75,"PASS WITH COACHING","FAIL"))) -> PASS
A5: QA-004 | B5: Everline Trading DMCC | C5: Casey Nguyen | D5: Pass | E5: Pass | F5: Pass | G5: Fail | H5: Pass | I5: Pass | J5: Pass | K5: Pass | L5: Escalation decision itself was correct and timely, but the file needs a written rationale, not just a timestamp — an examiner reviewing this file six months from now has no way to reconstruct why this was escalated. Coaching point: every escalation needs 2-3 sentences of documented reasoning, even when the outcome is clearly correct. | M5: =(COUNTIF(D5:K5,"Pass")*1+COUNTIF(D5:K5,"Partial")*0.5)/8 -> 0.875 | N5: =IF(OR(F5="Fail",J5="Fail",K5="Fail"),"YES","NO") -> NO | O5: =IF(N5="YES","FAIL - Critical Error",IF(M5>=0.9,"PASS",IF(M5>=0.75,"PASS WITH COACHING","FAIL"))) -> PASS WITH COACHING
A6: QA-005 | B6: Anatoly Sokolov | C6: Morgan Hale | D6: Pass | E6: Pass | F6: Pass | G6: Pass | H6: Pass | I6: Pass | J6: Pass | K6: Pass | L6: Excellent SAR file — clear narrative, well-documented pattern, correctly escalated and filed. | M6: =(COUNTIF(D6:K6,"Pass")*1+COUNTIF(D6:K6,"Partial")*0.5)/8 -> 1 | N6: =IF(OR(F6="Fail",J6="Fail",K6="Fail"),"YES","NO") -> NO | O6: =IF(N6="YES","FAIL - Critical Error",IF(M6>=0.9,"PASS",IF(M6>=0.75,"PASS WITH COACHING","FAIL"))) -> PASS
A7: QA-006 | B7: Consolidated Metals JSC | C7: Riley Chen | D7: Fail | E7: Pass | F7: Pass | G7: Partial | H7: Pass | I7: Fail | J7: Fail | K7: Fail | L7: Critical finding: the RFI response was accepted at face value without cross-referencing the business activity already documented in the KYC record, which describes a materially different business purpose. This is exactly the kind of inconsistency an RFI review exists to catch. Should have been escalated for further review; instead the case was closed. File must be reopened and reviewed by a senior investigator. | M7: =(COUNTIF(D7:K7,"Pass")*1+COUNTIF(D7:K7,"Partial")*0.5)/8 -> 0.4375 | N7: =IF(OR(F7="Fail",J7="Fail",K7="Fail"),"YES","NO") -> YES | O7: =IF(N7="YES","FAIL - Critical Error",IF(M7>=0.9,"PASS",IF(M7>=0.75,"PASS WITH COACHING","FAIL"))) -> FAIL - Critical Error
A8: QA-007 | B8: Silverline Trading FZE | C8: Casey Nguyen | D8: Pass | E8: Pass | F8: Fail | G8: Partial | H8: Pass | I8: Pass | J8: Fail | K8: Fail | L8: Critical finding: the case tool's own link-analysis panel showed the same funds moving through two related accounts within 48 hours, and this was not reviewed. This is not a subtle miss — the linkage was visible in a standard part of the case tool. File must be reopened; recommend refresher training on the link-analysis feature for this analyst. | M8: =(COUNTIF(D8:K8,"Pass")*1+COUNTIF(D8:K8,"Partial")*0.5)/8 -> 0.5625 | N8: =IF(OR(F8="Fail",J8="Fail",K8="Fail"),"YES","NO") -> YES | O8: =IF(N8="YES","FAIL - Critical Error",IF(M8>=0.9,"PASS",IF(M8>=0.75,"PASS WITH COACHING","FAIL"))) -> FAIL - Critical Error
A9: QA-008 | B9: Global Freight Solutions Ltd | C9: Riley Chen | D9: Partial | E9: Pass | F9: Pass | G9: Partial | H9: Pass | I9: Pass | J9: Pass | K9: Pass | L9: Underlying decision to continue the relationship is well-supported, but two things need tightening: the expired beneficial-owner ID should have been flagged for refresh, and the written rationale for continuing the relationship is lighter than our high-risk EDD standard. Coaching point, not a rework — the analytical conclusion itself is sound. | M9: =(COUNTIF(D9:K9,"Pass")*1+COUNTIF(D9:K9,"Partial")*0.5)/8 -> 0.875 | N9: =IF(OR(F9="Fail",J9="Fail",K9="Fail"),"YES","NO") -> NO | O9: =IF(N9="YES","FAIL - Critical Error",IF(M9>=0.9,"PASS",IF(M9>=0.75,"PASS WITH COACHING","FAIL"))) -> PASS WITH COACHING
A10: QA-009 | B10: Northbridge Capital Partners | C10: Taylor Brooks | D10: Pass | E10: Pass | F10: Pass | G10: Fail | H10: Fail | I10: Fail | J10: Fail | K10: Fail | L10: Critical finding: a confirmed regulatory-action adverse media hit was dismissed with a one-line note and no documented analysis. Policy requires MLRO escalation for any confirmed regulatory-action hit; this did not happen. Clearing this file is not supportable on the documentation present. Must be reopened and escalated immediately. | M10: =(COUNTIF(D10:K10,"Pass")*1+COUNTIF(D10:K10,"Partial")*0.5)/8 -> 0.375 | N10: =IF(OR(F10="Fail",J10="Fail",K10="Fail"),"YES","NO") -> YES | O10: =IF(N10="YES","FAIL - Critical Error",IF(M10>=0.9,"PASS",IF(M10>=0.75,"PASS WITH COACHING","FAIL"))) -> FAIL - Critical Error
A11: QA-010 | B11: Amara Diallo | C11: Jordan Ellis | D11: Fail | E11: Partial | F11: Partial | G11: Fail | H11: Fail | I11: Pass | J11: Pass | K11: Partial | L11: Multiple non-critical gaps compound into a weak file: no documented comparison against account history, typology indicators only partially noted rather than walked through, and no risk-rating cross-check. Scored as a non-critical FAIL rather than a critical failure because the underlying transaction pattern, independently re-reviewed, does not itself appear to meet the threshold for escalation — the disposition reached is probably right, but the file as written doesn't demonstrate that, which is itself the deficiency. Requires rework and refresher coaching on documentation standards. | M11: =(COUNTIF(D11:K11,"Pass")*1+COUNTIF(D11:K11,"Partial")*0.5)/8 -> 0.4375 | N11: =IF(OR(F11="Fail",J11="Fail",K11="Fail"),"YES","NO") -> NO | O11: =IF(N11="YES","FAIL - Critical Error",IF(M11>=0.9,"PASS",IF(M11>=0.75,"PASS WITH COACHING","FAIL"))) -> FAIL

Sheet QA_Dashboard
A1: QA DASHBOARD — Overall Outcomes
A3: Outcome | B3: Case Count | C3: % of Cases
A4: PASS | B4: =COUNTIF(QA_Review!$O$2:$O$11,"PASS") -> 3 | C4: =B4/10 -> 0.3
A5: PASS WITH COACHING | B5: =COUNTIF(QA_Review!$O$2:$O$11,"PASS WITH COACHING") -> 3 | C5: =B5/10 -> 0.3
A6: FAIL | B6: =COUNTIF(QA_Review!$O$2:$O$11,"FAIL") -> 1 | C6: =B6/10 -> 0.1
A7: FAIL - Critical Error | B7: =COUNTIF(QA_Review!$O$2:$O$11,"FAIL - Critical Error") -> 3 | C7: =B7/10 -> 0.3
A10: Pass Rate by Criterion (Pass or Partial credit shown separately)
A12: Criterion | B12: % Pass | C12: % Fail
A13: KYC information reviewed correctly? | B13: =COUNTIF(QA_Review!$D$2:$D$11,"Pass")/10 -> 0.7 | C13: =COUNTIF(QA_Review!$D$2:$D$11,"Fail")/10 -> 0.2
A14: Customer risk rating appropriate? | B14: =COUNTIF(QA_Review!$E$2:$E$11,"Pass")/10 -> 0.9 | C14: =COUNTIF(QA_Review!$E$2:$E$11,"Fail")/10 -> 0
A15: Transaction red flags identified? | B15: =COUNTIF(QA_Review!$F$2:$F$11,"Pass")/10 -> 0.8 | C15: =COUNTIF(QA_Review!$F$2:$F$11,"Fail")/10 -> 0.1
A16: Investigation sufficiently documented? | B16: =COUNTIF(QA_Review!$G$2:$G$11,"Pass")/10 -> 0.3 | C16: =COUNTIF(QA_Review!$G$2:$G$11,"Fail")/10 -> 0.3
A17: RFI appropriate? | B17: =COUNTIF(QA_Review!$H$2:$H$11,"Pass")/10 -> 0.7 | C17: =COUNTIF(QA_Review!$H$2:$H$11,"Fail")/10 -> 0.2
A18: Adverse media properly assessed? | B18: =COUNTIF(QA_Review!$I$2:$I$11,"Pass")/10 -> 0.8 | C18: =COUNTIF(QA_Review!$I$2:$I$11,"Fail")/10 -> 0.2
A19: Escalation required? | B19: =COUNTIF(QA_Review!$J$2:$J$11,"Pass")/10 -> 0.7 | C19: =COUNTIF(QA_Review!$J$2:$J$11,"Fail")/10 -> 0.3
A20: Final disposition supported by evidence? | B20: =COUNTIF(QA_Review!$K$2:$K$11,"Pass")/10 -> 0.6 | C20: =COUNTIF(QA_Review!$K$2:$K$11,"Fail")/10 -> 0.3
A23: Per-Analyst Summary
A25: Analyst | B25: Cases Reviewed | C25: Avg Score | D25: Critical Failures
A26: Casey Nguyen | B26: =COUNTIF(QA_Review!$C$2:$C$11,"Casey Nguyen") -> 2 | C26: =AVERAGEIF(QA_Review!$C$2:$C$11,"Casey Nguyen",QA_Review!$M$2:$M$11) -> 0.71875 | D26: =COUNTIFS(QA_Review!$C$2:$C$11,"Casey Nguyen",QA_Review!$N$2:$N$11,"YES") -> 1
A27: Jordan Ellis | B27: =COUNTIF(QA_Review!$C$2:$C$11,"Jordan Ellis") -> 2 | C27: =AVERAGEIF(QA_Review!$C$2:$C$11,"Jordan Ellis",QA_Review!$M$2:$M$11) -> 0.71875 | D27: =COUNTIFS(QA_Review!$C$2:$C$11,"Jordan Ellis",QA_Review!$N$2:$N$11,"YES") -> 0
A28: Morgan Hale | B28: =COUNTIF(QA_Review!$C$2:$C$11,"Morgan Hale") -> 2 | C28: =AVERAGEIF(QA_Review!$C$2:$C$11,"Morgan Hale",QA_Review!$M$2:$M$11) -> 0.9375 | D28: =COUNTIFS(QA_Review!$C$2:$C$11,"Morgan Hale",QA_Review!$N$2:$N$11,"YES") -> 0
A29: Riley Chen | B29: =COUNTIF(QA_Review!$C$2:$C$11,"Riley Chen") -> 2 | C29: =AVERAGEIF(QA_Review!$C$2:$C$11,"Riley Chen",QA_Review!$M$2:$M$11) -> 0.65625 | D29: =COUNTIFS(QA_Review!$C$2:$C$11,"Riley Chen",QA_Review!$N$2:$N$11,"YES") -> 1
A30: Taylor Brooks | B30: =COUNTIF(QA_Review!$C$2:$C$11,"Taylor Brooks") -> 2 | C30: =AVERAGEIF(QA_Review!$C$2:$C$11,"Taylor Brooks",QA_Review!$M$2:$M$11) -> 0.6875 | D30: =COUNTIFS(QA_Review!$C$2:$C$11,"Taylor Brooks",QA_Review!$N$2:$N$11,"YES") -> 1
